src/__init__.py
src/__main__.py
src/app.py
src/commandline.py
src/data.py
src/input.py
src/installer.py
src/keyboard.test.py
src/player.py
src/setup.py
src/stream.py
src/ui.py
PlayQuick-0.1.0.dist-info/METADATA
PlayQuick-0.1.0.dist-info/WHEEL
PlayQuick-0.1.0.dist-info/entry_points.txt
PlayQuick-0.1.0.dist-info/top_level.txt
PlayQuick-0.1.0.dist-info/RECORD
