Metadata-Version: 2.1
Name: PlayQuick
Version: 0.1.0
Summary: PlayQuick is a Simple media player that has UI and works on a console.
Home-page: https://github.com/beatbox4108/PlayQuick
Author: beatbox4108
Author-email: 68136638+beatbox4108@users.noreply.github.com
Classifier: Programming Language :: Python :: 3
Classifier: License :: OSI Approved :: MIT License
Classifier: Operating System :: OS Independent
Requires-Python: >=3.7
Requires-Dist: numpy
Requires-Dist: rich
Requires-Dist: pydub
